clientlib/__init__.py
clientlib/authentication.py
clientlib/clients.py
clientlib/endpoints.py
clientlib/exceptions.py
clientlib/functions.py
clientlib/models.py
clientlib/requests.py
clientlib-0.2.0.dist-info/LICENSE
clientlib-0.2.0.dist-info/METADATA
clientlib-0.2.0.dist-info/WHEEL
clientlib-0.2.0.dist-info/top_level.txt
clientlib-0.2.0.dist-info/zip-safe
clientlib-0.2.0.dist-info/RECORD
