Metadata-Version: 2.1
Name: clientlib
Version: 0.2.0
Summary: HTTP API client framework
Home-page: https://github.com/pmatigakis/clientlib
Author: Panagiotis Matigakis
Author-email: pmatigakis@gmail.com
License: UNKNOWN
Platform: UNKNOWN
Classifier: Development Status :: 3 - Alpha
Classifier: Programming Language :: Python :: 3
Classifier: Programming Language :: Python :: 3.5
Classifier: Programming Language :: Python :: 3.6
Classifier: Programming Language :: Python :: 3.7
Classifier: Programming Language :: Python :: 3.8
Classifier: License :: OSI Approved :: MIT License
Classifier: Operating System :: OS Independent
Classifier: Topic :: Software Development :: Libraries
Requires-Dist: requests (<3.0.0,>=2.18.4)
Requires-Dist: marshmallow (<4.0.0,>=3.0.0)
